{"Session data": "From 2022-05-21, 20:52:50 to 2022-05-21, 21:39:56", "Session": "00:47h", "Raw XP Gain": 431417, "XP Gain": 647123, "Raw XP/h": 782036, "XP/h": 1173054, "Loot": 114661, "Supplies": 83053, "Balance": 31608, "Damage": 608559, "Damage/h": 608559, "Healing": 137930, "Healing/h": 137930, "Killed Monsters": [{"Count": 24, "Name": "behemoth"}, {"Count": 1, "Name": "cave rat"}, {"Count": 6, "Name": "centipede"}, {"Count": 75, "Name": "clay guardian"}, {"Count": 19, "Name": "eternal guardian"}, {"Count": 24, "Name": "gargoyle"}, {"Count": 13, "Name": "hydra"}, {"Count": 34, "Name": "medusa"}, {"Count": 77, "Name": "omnivora"}, {"Count": 4, "Name": "poison spider"}, {"Count": 24, "Name": "serpent spawn"}, {"Count": 4, "Name": "slime"}, {"Count": 2, "Name": "souleater"}, {"Count": 26, "Name": "stone golem"}, {"Count": 1, "Name": "tarantula"}, {"Count": 2, "Name": "wasp"}], "Looted Items": [{"Count": 5, "Name": "a great mana potion"}, {"Count": 1, "Name": "terra boots"}, {"Count": 1, "Name": "a golden mug"}, {"Count": 1, "Name": "a crystal necklace"}, {"Count": 1, "Name": "a small sapphire"}, {"Count": 2, "Name": "a small emerald"}, {"Count": 4, "Name": "a small amethyst"}, {"Count": 171, "Name": "a platinum coin"}, {"Count": 1, "Name": "a life ring"}, {"Count": 1, "Name": "a ring of healing"}, {"Count": 17, "Name": "a blank rune"}, {"Count": 1, "Name": "a giant sword"}, {"Count": 1, "Name": "a carlin sword"}, {"Count": 1, "Name": "a guardian halberd"}, {"Count": 2, "Name": "a knight armor"}, {"Count": 1, "Name": "a crown armor"}, {"Count": 1, "Name": "a medusa shield"}, {"Count": 4, "Name": "a strawberry"}, {"Count": 3, "Name": "a green mushroom"}, {"Count": 1, "Name": "iron ore"}, {"Count": 1, "Name": "a perfect behemoth fang"}, {"Count": 1, "Name": "a death ring"}, {"Count": 7, "Name": "an assassin star"}, {"Count": 3, "Name": "a titan axe"}, {"Count": 4, "Name": "an ultimate health potion"}, {"Count": 2, "Name": "a cucumber"}, {"Count": 1, "Name": "a spellbook of enlightenment"}, {"Count": 1, "Name": "a slightly rusted armor"}, {"Count": 1, "Name": "a sacred tree amulet"}, {"Count": 5, "Name": "an ancient stone"}, {"Count": 5, "Name": "a snake skin"}, {"Count": 2, "Name": "a stone wing"}, {"Count": 22, "Name": "a lump of earth"}, {"Count": 3, "Name": "a strand of medusa hair"}, {"Count": 1, "Name": "a spiked iron ball"}, {"Count": 2, "Name": "a clay lump"}, {"Count": 1, "Name": "a battle stone"}, {"Count": 1, "Name": "a green crystal splinter"}, {"Count": 1, "Name": "a blue crystal splinter"}], "From": 1653177170.0, "To": 1653179996.0}