{"Session data": "From 2022-07-23, 07:13:12 to 2022-07-23, 08:21:33", "Session": "01:08h", "Raw XP Gain": 2558900, "XP Gain": 4670281, "Raw XP/h": 1975576, "XP/h": 2963365, "Loot": 539135, "Supplies": 370694, "Balance": 168441, "Damage": 2395290, "Damage/h": 2103871, "Healing": 787312, "Healing/h": 713179, "Killed Monsters": [{"Count": 193, "Name": "dawnfire asura"}, {"Count": 81, "Name": "frost flower asura"}, {"Count": 197, "Name": "hellspawn"}, {"Count": 224, "Name": "midnight asura"}], "Looted Items": [{"Count": 23, "Name": "a great mana potion"}, {"Count": 2, "Name": "a magma coat"}, {"Count": 1, "Name": "a ruby necklace"}, {"Count": 34, "Name": "a white pearl"}, {"Count": 20, "Name": "a black pearl"}, {"Count": 62, "Name": "a small diamond"}, {"Count": 39, "Name": "a small sapphire"}, {"Count": 22, "Name": "a small ruby"}, {"Count": 473, "Name": "a gold coin"}, {"Count": 19, "Name": "a small emerald"}, {"Count": 13, "Name": "a small amethyst"}, {"Count": 1245, "Name": "a platinum coin"}, {"Count": 4, "Name": "a yellow gem"}, {"Count": 1, "Name": "a red gem"}, {"Count": 2, "Name": "a blue gem"}, {"Count": 6, "Name": "a necrotic rod"}, {"Count": 2, "Name": "a wand of inferno"}, {"Count": 5, "Name": "a warrior helmet"}, {"Count": 5, "Name": "knight legs"}, {"Count": 3, "Name": "a blue robe"}, {"Count": 18, "Name": "a red mushroom"}, {"Count": 5, "Name": "a red piece of cloth"}, {"Count": 73, "Name": "a soul orb"}, {"Count": 71, "Name": "demonic essence"}, {"Count": 122, "Name": "a flask of demonic blood"}, {"Count": 114, "Name": "an assassin star"}, {"Count": 1, "Name": "an assassin dagger"}, {"Count": 1, "Name": "a berserk potion"}, {"Count": 1, "Name": "a spiked squelcher"}, {"Count": 17, "Name": "an ultimate health potion"}, {"Count": 2, "Name": "a focus cape"}, {"Count": 2, "Name": "a northwind rod"}, {"Count": 2, "Name": "a rusted armor"}, {"Count": 34, "Name": "a small topaz"}, {"Count": 31, "Name": "a hellspawn tail"}, {"Count": 77, "Name": "a golden lotus brooch"}, {"Count": 68, "Name": "a peacock feather fan"}, {"Count": 2, "Name": "oriental shoes"}], "From": 1658571192.0, "To": 1658575293.0}