{"Session data": "From 2022-06-13, 10:44:39 to 2022-06-13, 11:17:40", "Session": "00:33h", "Raw XP Gain": "102,485", "XP Gain": "153,725", "Raw XP/h": "183,064", "XP/h": "274,595", "Loot": "16,398", "Supplies": "17,606", "Balance": "-1,208", "Damage": "154,241", "Damage/h": "154,241", "Healing": "33,980", "Healing/h": "33,980", "Killed Monsters": [{"Count": "  18", "Name": "acid blob"}, {"Count": "  18", "Name": "bog raider"}, {"Count": "  11", "Name": "death blob"}, {"Count": "  1", "Name": "diseased Dan"}, {"Count": "  44", "Name": "mercury blob"}, {"Count": "  4", "Name": "mutated bat"}, {"Count": "  195", "Name": "mutated human"}, {"Count": "  47", "Name": "mutated rat"}, {"Count": "  8", "Name": "nightmare"}, {"Count": "  3", "Name": "nightmare scion"}, {"Count": "  11", "Name": "slime"}, {"Count": "  4", "Name": "spit nettle"}], "Looted Items": [{"Count": "  2", "Name": "a peanut"}, {"Count": "  9899", "Name": "a gold coin"}, {"Count": "  2", "Name": "a strange talisman"}, {"Count": "  1", "Name": "a sword"}, {"Count": "  1", "Name": "an obsidian lance"}, {"Count": "  1", "Name": "a scale armor"}, {"Count": "  27", "Name": "a worm"}, {"Count": "  12", "Name": "cheese"}, {"Count": "  3", "Name": "a soul orb"}, {"Count": "  1", "Name": "demonic essence"}, {"Count": "  3", "Name": "a flask of demonic blood"}, {"Count": "  1", "Name": "a heavily rusted armor"}, {"Count": "  6", "Name": "a glob of mercury"}, {"Count": "  1", "Name": "a glob of tar"}, {"Count": "  1", "Name": "a mutated bat ear"}, {"Count": "  5", "Name": "boggy dreads"}, {"Count": "  2", "Name": "a mutated rat tail"}, {"Count": "  38", "Name": "mutated flesh"}, {"Count": "  1", "Name": "a scythe leg"}]}