{"Session data": "From 2022-07-27, 09:35:45 to 2022-07-27, 10:30:23", "Session": "00:54h", "Raw XP Gain": "1,387,019", "XP Gain": "2,080,526", "Raw XP/h": "1,753,073", "XP/h": "2,629,610", "Loot": "396,556", "Supplies": "152,295", "Balance": "244,261", "Damage": "1,680,892", "Damage/h": "1,680,892", "Healing": "320,293", "Healing/h": "320,293", "Killed Monsters": [{"Count": "  104", "Name": "eternal guardian"}, {"Count": "  69", "Name": "hydra"}, {"Count": "  141", "Name": "medusa"}, {"Count": "  93", "Name": "serpent spawn"}, {"Count": "  148", "Name": "souleater"}], "Looted Items": [{"Count": "  37", "Name": "a great mana potion"}, {"Count": "  7", "Name": "a terra amulet"}, {"Count": "  209", "Name": "a small stone"}, {"Count": "  4", "Name": "a golden mug"}, {"Count": "  16", "Name": "a small sapphire"}, {"Count": "  17", "Name": "a small emerald"}, {"Count": "  933", "Name": "a platinum coin"}, {"Count": "  6", "Name": "a life ring"}, {"Count": "  1", "Name": "a life crystal"}, {"Count": "  3", "Name": "a necrotic rod"}, {"Count": "  3", "Name": "a wand of cosmic energy"}, {"Count": "  1", "Name": "a stone skin amulet"}, {"Count": "  1", "Name": "a ring of healing"}, {"Count": "  1", "Name": "a guardian halberd"}, {"Count": "  4", "Name": "a knight armor"}, {"Count": "  2", "Name": "a crown armor"}, {"Count": "  6", "Name": "a medusa shield"}, {"Count": "  18", "Name": "a green mushroom"}, {"Count": "  1", "Name": "a spirit container"}, {"Count": "  4", "Name": "a mercenary sword"}, {"Count": "  2", "Name": "a titan axe"}, {"Count": "  1", "Name": "a noble axe"}, {"Count": "  31", "Name": "an ultimate health potion"}, {"Count": "  2", "Name": "a cucumber"}, {"Count": "  2", "Name": "a slightly rusted armor"}, {"Count": "  22", "Name": "an ancient stone"}, {"Count": "  12", "Name": "a snake skin"}, {"Count": "  11", "Name": "a hydra head"}, {"Count": "  13", "Name": "a strand of medusa hair"}, {"Count": "  1", "Name": "a shiny stone"}, {"Count": "  2", "Name": "a winged tail"}, {"Count": "  1", "Name": "a Zaoan halberd"}, {"Count": "  14", "Name": "a spiked iron ball"}, {"Count": "  18", "Name": "a lizard essence"}, {"Count": "  1", "Name": "coal"}]}